<text>
<url>
http://kindleworld.blogspot.com/2009/04/mobile-versions-of-webpages-for-kindle.html</url>
<total_score>
<wrapper_score>
<score>
compound:0.0      </score>
<score>
neg:0.0      </score>
<score>
neu:1.0      </score>
<score>
pos:0.0      </score>
</wrapper_score>
<wrapper_score>
<score>
compound:0.0      </score>
<score>
neg:0.0      </score>
<score>
neu:1.0      </score>
<score>
pos:0.0      </score>
</wrapper_score>
<wrapper_score>
<score>
compound:-0.296      </score>
<score>
neg:0.688      </score>
<score>
neu:0.312      </score>
<score>
pos:0.0      </score>
</wrapper_score>
<wrapper_score>
<score>
compound:0.5106      </score>
<score>
neg:0.0      </score>
<score>
neu:0.732      </score>
<score>
pos:0.268      </score>
</wrapper_score>
<wrapper_score>
<score>
compound:0.4215      </score>
<score>
neg:0.0      </score>
<score>
neu:0.833      </score>
<score>
pos:0.167      </score>
</wrapper_score>
</total_score>
<summary>
It's easier to navigate than usual feeds, and you can read the latest 20 articles.
For 99 cents/mo., or 3 cents/day, the full text of this blog's most recent 20 articles is delivered (w/ images) to your Kindle whenever there's a new entry or updated information.
U.S./International (except UK) Edition: Click here for a 14-day free trial .
Each Kindle delivery replaces the previous one.
No clutter.
</summary>
<keywords>
['usual', 'world', 'theres', '20', 'text', 'browser', 'articles', 'webpages', 'blog', 'updated', 'uk', 'mobile', 'versions', 'w', 'web', 'kindle', 'trial']
</keywords>
<date>
None
</date>
</text>
